{
    "apiVersion": "v1",
    "kind": "Service",
    "metadata": {
      "annotations": {
        "kompose.cmd": "kompose convert --provider=openshift --build=build-config --build-repo=https://github.com/bcgov/moh-prime.git",
        "kompose.version": "1.18.0 (06a2e56)"
      },
      "creationTimestamp": null,
      "labels": {
        "io.kompose.service": "nginx-angular"
      },
      "name": "nginx-angular"
    },
    "spec": {
      "ports": [
        {
          "name": "8080",
          "port": 8080,
          "targetPort": 8080
        }
      ],
      "selector": {
        "io.kompose.service": "nginx-angular"
      }
    },
    "status": {
      "loadBalancer": {}
    }
  }